smalld_click/__init__.py
smalld_click/conversation.py
smalld_click/smalld_click.py
smalld_click/utils.py
smalld_click-0.2.2.dist-info/LICENSE.txt
smalld_click-0.2.2.dist-info/METADATA
smalld_click-0.2.2.dist-info/WHEEL
smalld_click-0.2.2.dist-info/top_level.txt
smalld_click-0.2.2.dist-info/RECORD
