Metadata-Version: 2.1
Name: smalld-click
Version: 0.2.2
Summary: Add Click support to your SmallD bot.
Home-page: https://github.com/aymanizz/smalld-click
Author: Ayman Izzeldin
Author-email: ayman.izzeldin@gmail.com
License: MIT
Platform: UNKNOWN
Classifier: Development Status :: 4 - Beta
Classifier: Intended Audience :: Developers
Classifier: License :: OSI Approved :: MIT License
Classifier: Programming Language :: Python :: 3
Classifier: Programming Language :: Python :: 3.6
Classifier: Programming Language :: Python :: 3.7
Classifier: Programming Language :: Python :: 3.8
Requires-Dist: smalld (>=0.1.4)
Requires-Dist: click (>=7.1.2)
